check_system/__init__.py
check_system/__main__.py
check_system/check_system.py
check_system-1.0.0.dist-info/LICENSE
check_system-1.0.0.dist-info/METADATA
check_system-1.0.0.dist-info/WHEEL
check_system-1.0.0.dist-info/entry_points.txt
check_system-1.0.0.dist-info/top_level.txt
check_system-1.0.0.dist-info/RECORD
