Metadata-Version: 2.1
Name: check-system
Version: 1.0.0
Summary: Tool for checking that a system is ok
Author-email: Viktor Rimark <python@rxbc.se>
Project-URL: homepage, https://blog.rxbc.se
Classifier: Development Status :: 4 - Beta
Classifier: Programming Language :: Python
Classifier: Programming Language :: Python :: 3
Classifier: Programming Language :: Python :: 3.6
Classifier: Programming Language :: Python :: 3.7
Classifier: Programming Language :: Python :: 3.8
Classifier: Programming Language :: Python :: 3.9
Classifier: Programming Language :: Python :: 3.10
Classifier: Programming Language :: Python :: 3.11
Classifier: Programming Language :: Python :: 3.12
Classifier: License :: OSI Approved :: MIT License
Requires-Python: >=3.6
License-File: LICENSE
Provides-Extra: dev
Requires-Dist: check-system[format] ; extra == 'dev'
Requires-Dist: check-system[lint] ; extra == 'dev'
Requires-Dist: check-system[test] ; extra == 'dev'
Provides-Extra: format
Requires-Dist: black ; extra == 'format'
Requires-Dist: isort ; extra == 'format'
Provides-Extra: lint
Requires-Dist: black ; extra == 'lint'
Requires-Dist: isort ; extra == 'lint'
Requires-Dist: pylint ; extra == 'lint'
Provides-Extra: test
Requires-Dist: pytest ; extra == 'test'
Requires-Dist: pytest-cov ; extra == 'test'
Provides-Extra: types
Requires-Dist: mypy ; extra == 'types'
